{".class": "MypyFile", "_fullname": "buffers.comparison_collector", "is_partial_stub_package": false, "is_stub": false, "names": {".class": "SymbolTable", "ComparisonCollector": {".class": "SymbolTableNode", "kind": "Gdef", "node": {".class": "TypeInfo", "_promote": null, "abstract_attributes": ["add_segment_pair", "label_unlabeled_comparisons"], "bases": ["abc.ABC"], "declared_metaclass": null, "defn": {".class": "ClassDef", "fullname": "buffers.comparison_collector.ComparisonCollector", "name": "ComparisonCollector", "type_vars": []}, "flags": ["is_abstract"], "fullname": "buffers.comparison_collector.ComparisonCollector", "metaclass_type": "abc.ABCMeta", "metadata": {}, "module_name": "buffers.comparison_collector", "mro": ["buffers.comparison_collector.ComparisonCollector", "abc.ABC", "builtins.object"], "names": {".class": "SymbolTable", "__init__": {".class": "SymbolTableNode", "kind": "Mdef", "node": {".class": "FuncDef", "arg_kinds": [0, 0, 0, 1, 1, 1, 1], "arg_names": ["self", "capacity_in_transitions", "label_scheduler", "collect_callable", "segment_length", "precollected_comparisons", "precollected_segments"], "flags": [], "fullname": "buffers.comparison_collector.ComparisonCollector.__init__", "name": "__init__", "type": null}}, "_capacity": {".class": "SymbolTableNode", "implicit": true, "kind": "Mdef", "node": {".class": "Var", "flags": [], "fullname": "buffers.comparison_collector.ComparisonCollector._capacity", "name": "_capacity", "type": {".class": "AnyType", "missing_import_name": null, "source_any": null, "type_of_any": 1}}}, "_comparisons": {".class": "SymbolTableNode", "implicit": true, "kind": "Mdef", "node": {".class": "Var", "flags": [], "fullname": "buffers.comparison_collector.ComparisonCollector._comparisons", "name": "_comparisons", "type": {".class": "AnyType", "missing_import_name": null, "source_any": null, "type_of_any": 1}}}, "_get_path_length": {".class": "SymbolTableNode", "kind": "Mdef", "node": {".class": "Decorator", "func": {".class": "FuncDef", "arg_kinds": [0], "arg_names": ["path"], "flags": ["is_static", "is_decorated"], "fullname": "buffers.comparison_collector.ComparisonCollector._get_path_length", "name": "_get_path_length", "type": null}, "is_overload": false, "var": {".class": "Var", "flags": ["is_initialized_in_class", "is_staticmethod", "is_ready"], "fullname": null, "name": "_get_path_length", "type": {".class": "CallableType", "arg_kinds": [0], "arg_names": ["path"], "arg_types": [{".class": "AnyType", "missing_import_name": null, "source_any": null, "type_of_any": 1}], "bound_args": [], "def_extras": {}, "fallback": "builtins.function", "implicit": true, "is_ellipsis_args": false, "name": "_get_path_length of ComparisonCollector", "ret_type": {".class": "AnyType", "missing_import_name": null, "source_any": null, "type_of_any": 1}, "variables": []}}}}, "_paths": {".class": "SymbolTableNode", "implicit": true, "kind": "Mdef", "node": {".class": "Var", "flags": [], "fullname": "buffers.comparison_collector.ComparisonCollector._paths", "name": "_paths", "type": {".class": "AnyType", "missing_import_name": null, "source_any": null, "type_of_any": 1}}}, "_segments": {".class": "SymbolTableNode", "implicit": true, "kind": "Mdef", "node": {".class": "Var", "flags": [], "fullname": "buffers.comparison_collector.ComparisonCollector._segments", "name": "_segments", "type": {".class": "AnyType", "missing_import_name": null, "source_any": null, "type_of_any": 1}}}, "add_episode_batch": {".class": "SymbolTableNode", "kind": "Mdef", "node": {".class": "FuncDef", "arg_kinds": [0, 0, 0, 0], "arg_names": ["self", "step_itr", "env_spec", "paths"], "flags": [], "fullname": "buffers.comparison_collector.ComparisonCollector.add_episode_batch", "name": "add_episode_batch", "type": null}}, "add_path": {".class": "SymbolTableNode", "kind": "Mdef", "node": {".class": "FuncDef", "arg_kinds": [0, 0], "arg_names": ["self", "path"], "flags": [], "fullname": "buffers.comparison_collector.ComparisonCollector.add_path", "name": "add_path", "type": null}}, "add_segment_pair": {".class": "SymbolTableNode", "kind": "Mdef", "node": {".class": "Decorator", "func": {".class": "FuncDef", "arg_kinds": [0, 0, 0], "arg_names": ["self", "left_seg", "right_sef"], "flags": ["is_decorated", "is_abstract"], "fullname": "buffers.comparison_collector.ComparisonCollector.add_segment_pair", "name": "add_segment_pair", "type": null}, "is_overload": false, "var": {".class": "Var", "flags": ["is_initialized_in_class", "is_ready"], "fullname": null, "name": "add_segment_pair", "type": {".class": "CallableType", "arg_kinds": [0, 0, 0], "arg_names": ["self", "left_seg", "right_sef"], "arg_types": ["buffers.comparison_collector.ComparisonCollector", {".class": "AnyType", "missing_import_name": null, "source_any": null, "type_of_any": 1}, {".class": "AnyType", "missing_import_name": null, "source_any": null, "type_of_any": 1}], "bound_args": [], "def_extras": {}, "fallback": "builtins.function", "implicit": true, "is_ellipsis_args": false, "name": "add_segment_pair of ComparisonCollector", "ret_type": {".class": "AnyType", "missing_import_name": null, "source_any": null, "type_of_any": 1}, "variables": []}}}}, "collect": {".class": "SymbolTableNode", "kind": "Mdef", "node": {".class": "FuncDef", "arg_kinds": [0, 0, 0, 0], "arg_names": ["self", "step_itr", "env_spec", "paths"], "flags": [], "fullname": "buffers.comparison_collector.ComparisonCollector.collect", "name": "collect", "type": null}}, "collect_callable": {".class": "SymbolTableNode", "implicit": true, "kind": "Mdef", "node": {".class": "Var", "flags": [], "fullname": "buffers.comparison_collector.ComparisonCollector.collect_callable", "name": "collect_callable", "type": {".class": "AnyType", "missing_import_name": null, "source_any": null, "type_of_any": 1}}}, "comps_to_segs": {".class": "SymbolTableNode", "kind": "Mdef", "node": {".class": "Decorator", "func": {".class": "FuncDef", "arg_kinds": [0], "arg_names": ["comps"], "flags": ["is_static", "is_decorated"], "fullname": "buffers.comparison_collector.ComparisonCollector.comps_to_segs", "name": "comps_to_segs", "type": null}, "is_overload": false, "var": {".class": "Var", "flags": ["is_initialized_in_class", "is_staticmethod", "is_ready"], "fullname": null, "name": "comps_to_segs", "type": {".class": "CallableType", "arg_kinds": [0], "arg_names": ["comps"], "arg_types": [{".class": "AnyType", "missing_import_name": null, "source_any": null, "type_of_any": 1}], "bound_args": [], "def_extras": {}, "fallback": "builtins.function", "implicit": true, "is_ellipsis_args": false, "name": "comps_to_segs of ComparisonCollector", "ret_type": {".class": "AnyType", "missing_import_name": null, "source_any": null, "type_of_any": 1}, "variables": []}}}}, "flush": {".class": "SymbolTableNode", "kind": "Mdef", "node": {".class": "FuncDef", "arg_kinds": [0], "arg_names": ["self"], "flags": [], "fullname": "buffers.comparison_collector.ComparisonCollector.flush", "name": "flush", "type": null}}, "get_pairwise_data": {".class": "SymbolTableNode", "kind": "Mdef", "node": {".class": "FuncDef", "arg_kinds": [0], "arg_names": ["self"], "flags": [], "fullname": "buffers.comparison_collector.ComparisonCollector.get_pairwise_data", "name": "get_pairwise_data", "type": null}}, "get_total_ordering_on_segments": {".class": "SymbolTableNode", "kind": "Mdef", "node": {".class": "FuncDef", "arg_kinds": [0], "arg_names": ["self"], "flags": [], "fullname": "buffers.comparison_collector.ComparisonCollector.get_total_ordering_on_segments", "name": "get_total_ordering_on_segments", "type": null}}, "get_totally_ordered_data": {".class": "SymbolTableNode", "kind": "Mdef", "node": {".class": "FuncDef", "arg_kinds": [0, 1], "arg_names": ["self", "epochs"], "flags": [], "fullname": "buffers.comparison_collector.ComparisonCollector.get_totally_ordered_data", "name": "get_totally_ordered_data", "type": null}}, "label_scheduler": {".class": "SymbolTableNode", "implicit": true, "kind": "Mdef", "node": {".class": "Var", "flags": [], "fullname": "buffers.comparison_collector.ComparisonCollector.label_scheduler", "name": "label_scheduler", "type": {".class": "AnyType", "missing_import_name": null, "source_any": null, "type_of_any": 1}}}, "label_unlabeled_comparisons": {".class": "SymbolTableNode", "kind": "Mdef", "node": {".class": "Decorator", "func": {".class": "FuncDef", "arg_kinds": [0], "arg_names": ["self"], "flags": ["is_decorated", "is_abstract"], "fullname": "buffers.comparison_collector.ComparisonCollector.label_unlabeled_comparisons", "name": "label_unlabeled_comparisons", "type": null}, "is_overload": false, "var": {".class": "Var", "flags": ["is_initialized_in_class", "is_ready"], "fullname": null, "name": "label_unlabeled_comparisons", "type": {".class": "CallableType", "arg_kinds": [0], "arg_names": ["self"], "arg_types": ["buffers.comparison_collector.ComparisonCollector"], "bound_args": [], "def_extras": {}, "fallback": "builtins.function", "implicit": true, "is_ellipsis_args": false, "name": "label_unlabeled_comparisons of ComparisonCollector", "ret_type": {".class": "AnyType", "missing_import_name": null, "source_any": null, "type_of_any": 1}, "variables": []}}}}, "labeled_comparisons": {".class": "SymbolTableNode", "kind": "Mdef", "node": {".class": "Decorator", "func": {".class": "FuncDef", "arg_kinds": [0], "arg_names": ["self"], "flags": ["is_property", "is_decorated"], "fullname": "buffers.comparison_collector.ComparisonCollector.labeled_comparisons", "name": "labeled_comparisons", "type": null}, "is_overload": false, "var": {".class": "Var", "flags": ["is_initialized_in_class", "is_property", "is_ready"], "fullname": null, "name": "labeled_comparisons", "type": {".class": "CallableType", "arg_kinds": [0], "arg_names": ["self"], "arg_types": ["buffers.comparison_collector.ComparisonCollector"], "bound_args": [], "def_extras": {}, "fallback": "builtins.function", "implicit": true, "is_ellipsis_args": false, "name": "labeled_comparisons of ComparisonCollector", "ret_type": {".class": "AnyType", "missing_import_name": null, "source_any": null, "type_of_any": 1}, "variables": []}}}}, "labeled_decisive_comparisons": {".class": "SymbolTableNode", "kind": "Mdef", "node": {".class": "Decorator", "func": {".class": "FuncDef", "arg_kinds": [0], "arg_names": ["self"], "flags": ["is_property", "is_decorated"], "fullname": "buffers.comparison_collector.ComparisonCollector.labeled_decisive_comparisons", "name": "labeled_decisive_comparisons", "type": null}, "is_overload": false, "var": {".class": "Var", "flags": ["is_initialized_in_class", "is_property", "is_ready"], "fullname": null, "name": "labeled_decisive_comparisons", "type": {".class": "CallableType", "arg_kinds": [0], "arg_names": ["self"], "arg_types": ["buffers.comparison_collector.ComparisonCollector"], "bound_args": [], "def_extras": {}, "fallback": "builtins.function", "implicit": true, "is_ellipsis_args": false, "name": "labeled_decisive_comparisons of ComparisonCollector", "ret_type": {".class": "AnyType", "missing_import_name": null, "source_any": null, "type_of_any": 1}, "variables": []}}}}, "n_transitions_stored": {".class": "SymbolTableNode", "implicit": true, "kind": "Mdef", "node": {".class": "Var", "flags": [], "fullname": "buffers.comparison_collector.ComparisonCollector.n_transitions_stored", "name": "n_transitions_stored", "type": {".class": "AnyType", "missing_import_name": null, "source_any": null, "type_of_any": 1}}}, "num_comparisons": {".class": "SymbolTableNode", "kind": "Mdef", "node": {".class": "Decorator", "func": {".class": "FuncDef", "arg_kinds": [0], "arg_names": ["self"], "flags": ["is_property", "is_decorated"], "fullname": "buffers.comparison_collector.ComparisonCollector.num_comparisons", "name": "num_comparisons", "type": null}, "is_overload": false, "var": {".class": "Var", "flags": ["is_initialized_in_class", "is_property", "is_ready"], "fullname": null, "name": "num_comparisons", "type": {".class": "CallableType", "arg_kinds": [0], "arg_names": ["self"], "arg_types": ["buffers.comparison_collector.ComparisonCollector"], "bound_args": [], "def_extras": {}, "fallback": "builtins.function", "implicit": true, "is_ellipsis_args": false, "name": "num_comparisons of ComparisonCollector", "ret_type": {".class": "AnyType", "missing_import_name": null, "source_any": null, "type_of_any": 1}, "variables": []}}}}, "requires_more_comparisons": {".class": "SymbolTableNode", "kind": "Mdef", "node": {".class": "FuncDef", "arg_kinds": [0, 0], "arg_names": ["self", "step_itr"], "flags": [], "fullname": "buffers.comparison_collector.ComparisonCollector.requires_more_comparisons", "name": "requires_more_comparisons", "type": null}}, "requires_more_labels": {".class": "SymbolTableNode", "kind": "Mdef", "node": {".class": "FuncDef", "arg_kinds": [0, 0], "arg_names": ["self", "step_itr"], "flags": [], "fullname": "buffers.comparison_collector.ComparisonCollector.requires_more_labels", "name": "requires_more_labels", "type": null}}, "sample_comparison": {".class": "SymbolTableNode", "kind": "Mdef", "node": {".class": "FuncDef", "arg_kinds": [0], "arg_names": ["self"], "flags": [], "fullname": "buffers.comparison_collector.ComparisonCollector.sample_comparison", "name": "sample_comparison", "type": null}}, "sample_path": {".class": "SymbolTableNode", "kind": "Mdef", "node": {".class": "FuncDef", "arg_kinds": [0], "arg_names": ["self"], "flags": [], "fullname": "buffers.comparison_collector.ComparisonCollector.sample_path", "name": "sample_path", "type": null}}, "sample_segment": {".class": "SymbolTableNode", "kind": "Mdef", "node": {".class": "FuncDef", "arg_kinds": [0], "arg_names": ["self"], "flags": [], "fullname": "buffers.comparison_collector.ComparisonCollector.sample_segment", "name": "sample_segment", "type": null}}, "segment_length": {".class": "SymbolTableNode", "implicit": true, "kind": "Mdef", "node": {".class": "Var", "flags": [], "fullname": "buffers.comparison_collector.ComparisonCollector.segment_length", "name": "segment_length", "type": {".class": "AnyType", "missing_import_name": null, "source_any": null, "type_of_any": 1}}}, "unlabeled_comparisons": {".class": "SymbolTableNode", "kind": "Mdef", "node": {".class": "Decorator", "func": {".class": "FuncDef", "arg_kinds": [0], "arg_names": ["self"], "flags": ["is_property", "is_decorated"], "fullname": "buffers.comparison_collector.ComparisonCollector.unlabeled_comparisons", "name": "unlabeled_comparisons", "type": null}, "is_overload": false, "var": {".class": "Var", "flags": ["is_initialized_in_class", "is_property", "is_ready"], "fullname": null, "name": "unlabeled_comparisons", "type": {".class": "CallableType", "arg_kinds": [0], "arg_names": ["self"], "arg_types": ["buffers.comparison_collector.ComparisonCollector"], "bound_args": [], "def_extras": {}, "fallback": "builtins.function", "implicit": true, "is_ellipsis_args": false, "name": "unlabeled_comparisons of ComparisonCollector", "ret_type": {".class": "AnyType", "missing_import_name": null, "source_any": null, "type_of_any": 1}, "variables": []}}}}}, "tuple_type": null, "type_vars": [], "typeddict_type": null}}, "HumanComparisonCollector": {".class": "SymbolTableNode", "kind": "Gdef", "node": {".class": "TypeInfo", "_promote": null, "abstract_attributes": [], "bases": ["buffers.comparison_collector.ComparisonCollector"], "declared_metaclass": null, "defn": {".class": "ClassDef", "fullname": "buffers.comparison_collector.HumanComparisonCollector", "name": "HumanComparisonCollector", "type_vars": []}, "flags": [], "fullname": "buffers.comparison_collector.HumanComparisonCollector", "metaclass_type": "abc.ABCMeta", "metadata": {}, "module_name": "buffers.comparison_collector", "mro": ["buffers.comparison_collector.HumanComparisonCollector", "buffers.comparison_collector.ComparisonCollector", "abc.ABC", "builtins.object"], "names": {".class": "SymbolTable", "__init__": {".class": "SymbolTableNode", "kind": "Mdef", "node": {".class": "FuncDef", "arg_kinds": [0, 0, 0, 0, 0, 1], "arg_names": ["self", "capacity_in_transitions", "label_scheduler", "env", "experiment_name", "segment_length"], "flags": [], "fullname": "buffers.comparison_collector.HumanComparisonCollector.__init__", "name": "__init__", "type": null}}, "_create_comparison_in_webapp": {".class": "SymbolTableNode", "kind": "Mdef", "node": {".class": "FuncDef", "arg_kinds": [0, 0, 0], "arg_names": ["self", "left_seg", "right_seg"], "flags": [], "fullname": "buffers.comparison_collector.HumanComparisonCollector._create_comparison_in_webapp", "name": "_create_comparison_in_webapp", "type": null}}, "add_segment_pair": {".class": "SymbolTableNode", "kind": "Mdef", "node": {".class": "FuncDef", "arg_kinds": [0, 0, 0], "arg_names": ["self", "left_seg", "right_seg"], "flags": [], "fullname": "buffers.comparison_collector.HumanComparisonCollector.add_segment_pair", "name": "add_segment_pair", "type": null}}, "convert_segment_to_media_url": {".class": "SymbolTableNode", "kind": "Mdef", "node": {".class": "FuncDef", "arg_kinds": [0, 0, 0, 0], "arg_names": ["self", "comparison_uuid", "side", "segment"], "flags": [], "fullname": "buffers.comparison_collector.HumanComparisonCollector.convert_segment_to_media_url", "name": "convert_segment_to_media_url", "type": null}}, "env": {".class": "SymbolTableNode", "implicit": true, "kind": "Mdef", "node": {".class": "Var", "flags": [], "fullname": "buffers.comparison_collector.HumanComparisonCollector.env", "name": "env", "type": {".class": "AnyType", "missing_import_name": null, "source_any": null, "type_of_any": 1}}}, "experiment_name": {".class": "SymbolTableNode", "implicit": true, "kind": "Mdef", "node": {".class": "Var", "flags": [], "fullname": "buffers.comparison_collector.HumanComparisonCollector.experiment_name", "name": "experiment_name", "type": {".class": "AnyType", "missing_import_name": null, "source_any": null, "type_of_any": 1}}}, "label_unlabeled_comparisons": {".class": "SymbolTableNode", "kind": "Mdef", "node": {".class": "FuncDef", "arg_kinds": [0], "arg_names": ["self"], "flags": [], "fullname": "buffers.comparison_collector.HumanComparisonCollector.label_unlabeled_comparisons", "name": "label_unlabeled_comparisons", "type": null}}}, "tuple_type": null, "type_vars": [], "typeddict_type": null}}, "LabelAnnealer": {".class": "SymbolTableNode", "kind": "Gdef", "node": {".class": "TypeInfo", "_promote": null, "abstract_attributes": [], "bases": ["builtins.object"], "declared_metaclass": null, "defn": {".class": "ClassDef", "fullname": "buffers.comparison_collector.LabelAnnealer", "name": "LabelAnnealer", "type_vars": []}, "flags": [], "fullname": "buffers.comparison_collector.LabelAnnealer", "metaclass_type": null, "metadata": {}, "module_name": "buffers.comparison_collector", "mro": ["buffers.comparison_collector.LabelAnnealer", "builtins.object"], "names": {".class": "SymbolTable", "__init__": {".class": "SymbolTableNode", "kind": "Mdef", "node": {".class": "FuncDef", "arg_kinds": [0, 0, 0, 0], "arg_names": ["self", "final_timesteps", "final_labels", "pretrain_labels"], "flags": [], "fullname": "buffers.comparison_collector.LabelAnnealer.__init__", "name": "__init__", "type": null}}, "_final_labels": {".class": "SymbolTableNode", "implicit": true, "kind": "Mdef", "node": {".class": "Var", "flags": [], "fullname": "buffers.comparison_collector.LabelAnnealer._final_labels", "name": "_final_labels", "type": {".class": "AnyType", "missing_import_name": null, "source_any": null, "type_of_any": 1}}}, "_final_timesteps": {".class": "SymbolTableNode", "implicit": true, "kind": "Mdef", "node": {".class": "Var", "flags": [], "fullname": "buffers.comparison_collector.LabelAnnealer._final_timesteps", "name": "_final_timesteps", "type": {".class": "AnyType", "missing_import_name": null, "source_any": null, "type_of_any": 1}}}, "n_desired_labels": {".class": "SymbolTableNode", "kind": "Mdef", "node": {".class": "FuncDef", "arg_kinds": [0, 0], "arg_names": ["self", "itr"], "flags": [], "fullname": "buffers.comparison_collector.LabelAnnealer.n_desired_labels", "name": "n_desired_labels", "type": null}}, "pretrain_labels": {".class": "SymbolTableNode", "implicit": true, "kind": "Mdef", "node": {".class": "Var", "flags": [], "fullname": "buffers.comparison_collector.LabelAnnealer.pretrain_labels", "name": "pretrain_labels", "type": {".class": "AnyType", "missing_import_name": null, "source_any": null, "type_of_any": 1}}}}, "tuple_type": null, "type_vars": [], "typeddict_type": null}}, "PathBuffer": {".class": "SymbolTableNode", "kind": "Gdef", "node": {".class": "Var", "flags": ["is_suppressed_import", "is_ready"], "fullname": "buffers.comparison_collector.PathBuffer", "name": "PathBuffer", "type": {".class": "AnyType", "missing_import_name": "buffers.comparison_collector.PathBuffer", "source_any": null, "type_of_any": 3}}}, "StepType": {".class": "SymbolTableNode", "kind": "Gdef", "node": {".class": "Var", "flags": ["is_suppressed_import", "is_ready"], "fullname": "buffers.comparison_collector.StepType", "name": "StepType", "type": {".class": "AnyType", "missing_import_name": "buffers.comparison_collector.StepType", "source_any": null, "type_of_any": 3}}}, "SyntheticComparisonCollector": {".class": "SymbolTableNode", "kind": "Gdef", "node": {".class": "TypeInfo", "_promote": null, "abstract_attributes": [], "bases": ["buffers.comparison_collector.ComparisonCollector"], "declared_metaclass": null, "defn": {".class": "ClassDef", "fullname": "buffers.comparison_collector.SyntheticComparisonCollector", "name": "SyntheticComparisonCollector", "type_vars": []}, "flags": [], "fullname": "buffers.comparison_collector.SyntheticComparisonCollector", "metaclass_type": "abc.ABCMeta", "metadata": {}, "module_name": "buffers.comparison_collector", "mro": ["buffers.comparison_collector.SyntheticComparisonCollector", "buffers.comparison_collector.ComparisonCollector", "abc.ABC", "builtins.object"], "names": {".class": "SymbolTable", "_add_synthetic_label": {".class": "SymbolTableNode", "kind": "Mdef", "node": {".class": "Decorator", "func": {".class": "FuncDef", "arg_kinds": [0], "arg_names": ["comparison"], "flags": ["is_static", "is_decorated"], "fullname": "buffers.comparison_collector.SyntheticComparisonCollector._add_synthetic_label", "name": "_add_synthetic_label", "type": null}, "is_overload": false, "var": {".class": "Var", "flags": ["is_initialized_in_class", "is_staticmethod", "is_ready"], "fullname": null, "name": "_add_synthetic_label", "type": {".class": "CallableType", "arg_kinds": [0], "arg_names": ["comparison"], "arg_types": [{".class": "AnyType", "missing_import_name": null, "source_any": null, "type_of_any": 1}], "bound_args": [], "def_extras": {}, "fallback": "builtins.function", "implicit": true, "is_ellipsis_args": false, "name": "_add_synthetic_label of SyntheticComparisonCollector", "ret_type": {".class": "AnyType", "missing_import_name": null, "source_any": null, "type_of_any": 1}, "variables": []}}}}, "add_segment_pair": {".class": "SymbolTableNode", "kind": "Mdef", "node": {".class": "FuncDef", "arg_kinds": [0, 0, 0], "arg_names": ["self", "left_seg", "right_seg"], "flags": [], "fullname": "buffers.comparison_collector.SyntheticComparisonCollector.add_segment_pair", "name": "add_segment_pair", "type": null}}, "label_unlabeled_comparisons": {".class": "SymbolTableNode", "kind": "Mdef", "node": {".class": "FuncDef", "arg_kinds": [0], "arg_names": ["self"], "flags": [], "fullname": "buffers.comparison_collector.SyntheticComparisonCollector.label_unlabeled_comparisons", "name": "label_unlabeled_comparisons", "type": null}}}, "tuple_type": null, "type_vars": [], "typeddict_type": null}}, "__doc__": {".class": "SymbolTableNode", "kind": "Gdef", "node": {".class": "Var", "flags": ["is_ready"], "fullname": "buffers.comparison_collector.__doc__", "name": "__doc__", "type": "builtins.str"}}, "__file__": {".class": "SymbolTableNode", "kind": "Gdef", "node": {".class": "Var", "flags": ["is_ready"], "fullname": "buffers.comparison_collector.__file__", "name": "__file__", "type": "builtins.str"}}, "__name__": {".class": "SymbolTableNode", "kind": "Gdef", "node": {".class": "Var", "flags": ["is_ready"], "fullname": "buffers.comparison_collector.__name__", "name": "__name__", "type": "builtins.str"}}, "__package__": {".class": "SymbolTableNode", "kind": "Gdef", "node": {".class": "Var", "flags": ["is_ready"], "fullname": "buffers.comparison_collector.__package__", "name": "__package__", "type": "builtins.str"}}, "_write_and_upload_video": {".class": "SymbolTableNode", "kind": "Gdef", "node": {".class": "FuncDef", "arg_kinds": [0, 0, 0, 0], "arg_names": ["env", "gcs_path", "local_path", "segment"], "flags": [], "fullname": "buffers.comparison_collector._write_and_upload_video", "name": "_write_and_upload_video", "type": null}}, "abc": {".class": "SymbolTableNode", "cross_ref": "abc", "kind": "Gdef"}, "always_true": {".class": "SymbolTableNode", "kind": "Gdef", "node": {".class": "FuncDef", "arg_kinds": [0], "arg_names": ["i"], "flags": [], "fullname": "buffers.comparison_collector.always_true", "name": "always_true", "type": null}}, "collections": {".class": "SymbolTableNode", "cross_ref": "collections", "kind": "Gdef"}, "logger": {".class": "SymbolTableNode", "kind": "Gdef", "node": {".class": "Var", "flags": ["is_suppressed_import", "is_ready"], "fullname": "buffers.comparison_collector.logger", "name": "logger", "type": {".class": "AnyType", "missing_import_name": "buffers.comparison_collector.logger", "source_any": null, "type_of_any": 3}}}, "multiprocessing": {".class": "SymbolTableNode", "cross_ref": "multiprocessing", "kind": "Gdef"}, "np": {".class": "SymbolTableNode", "kind": "Gdef", "node": {".class": "Var", "flags": ["is_suppressed_import", "is_ready"], "fullname": "buffers.comparison_collector.np", "name": "np", "type": {".class": "AnyType", "missing_import_name": "buffers.comparison_collector.np", "source_any": null, "type_of_any": 3}}}, "os": {".class": "SymbolTableNode", "cross_ref": "os", "kind": "Gdef"}, "time": {".class": "SymbolTableNode", "cross_ref": "time", "kind": "Gdef"}, "torch": {".class": "SymbolTableNode", "cross_ref": "torch", "kind": "Gdef"}, "upload_to_gcs": {".class": "SymbolTableNode", "cross_ref": "utils.video.upload_to_gcs", "kind": "Gdef"}, "uuid": {".class": "SymbolTableNode", "cross_ref": "uuid", "kind": "Gdef"}, "write_segment_to_video": {".class": "SymbolTableNode", "cross_ref": "utils.video.write_segment_to_video", "kind": "Gdef"}}, "path": "/home/jamesborg/workspace/robust_rewards_from_preferences/buffers/comparison_collector.py"}